mentorhub_flask_utils/__init__.py
mentorhub_flask_utils/breadcrumb.py
mentorhub_flask_utils/ejson_encoder.py
mentorhub_flask_utils/test_breadcrumb.py
mentorhub_flask_utils/test_token.py
mentorhub_flask_utils/token.py
mentorhub_flask_utils-1.0.2.dist-info/LICENSE
mentorhub_flask_utils-1.0.2.dist-info/METADATA
mentorhub_flask_utils-1.0.2.dist-info/WHEEL
mentorhub_flask_utils-1.0.2.dist-info/top_level.txt
mentorhub_flask_utils-1.0.2.dist-info/RECORD
