Metadata-Version: 2.1
Name: mentorhub-flask-utils
Version: 1.0.2
Summary: Flask helper utilities for Mentorhub API projects
Home-page: https://github.com/agile-learning-institute/mentorHub-flask-utils
Author: Agile Learning Institute
Author-email: devs@agile-learning.institute
License: Apache-2.0
Classifier: Programming Language :: Python :: 3
Classifier: License :: OSI Approved :: Apache Software License
Classifier: Operating System :: OS Independent
Requires-Python: >=3.6
License-File: LICENSE
Requires-Dist: flask
Requires-Dist: pymongo
